irons/Software/__init__.py
irons/Software/bias_correction.py
irons/Software/cum2inst.py
irons/Software/day2week2month.py
irons/Software/download_forecast.py
irons/Software/HBV model structure.png
irons/Software/HBV_calibration.py
irons/Software/HBV_sim.py
irons/Software/operating_policy.py
irons/Software/read_data.py
irons/Software/res_sys_sim.py
irons/Software/res_sys_sim_diagram.png
irons/Software/test_functions/__init__.py
irons/Software/test_functions/test_bias_correction.py
irons/Software/test_functions/test_cum2inst.py
irons/Software/test_functions/test_day2week2month.py
irons/Software/test_functions/test_HBV_sim.py
irons/Software/test_functions/test_res_sys_sim.py
irons-1.0.dist-info/LICENSE.md
irons-1.0.dist-info/WHEEL
irons-1.0.dist-info/METADATA
irons-1.0.dist-info/RECORD
